eeharvest/__init__.py
eeharvest/arc2meter.py
eeharvest/harvester.py
eeharvest/msg.py
eeharvest/settings.py
eeharvest/utils.py
eeharvest/data/config.yaml
eeharvest/data/schema.yaml
eeharvest/data/template.yaml
eeharvest-1.6.0.dist-info/LICENSE.txt
eeharvest-1.6.0.dist-info/METADATA
eeharvest-1.6.0.dist-info/WHEEL
eeharvest-1.6.0.dist-info/top_level.txt
eeharvest-1.6.0.dist-info/RECORD
