Metadata-Version: 2.1
Name: eeharvest
Version: 1.6.0
Summary: An automated, convenient downloader for Google Earth Engine datasets in Python
Home-page: https://github.com/sydney-informatics-hub/eeharvest
Author: Januar Harianto
Author-email: januar.harianto@sydney.edu.au
License: LGPL-3.0-or-later
Project-URL: Documentation, https://github.com/sydney-informatics-hub/eeharvest
Platform: any
Classifier: Development Status :: 4 - Beta
Classifier: Programming Language :: Python
Requires-Python: >=3.8
License-File: LICENSE.txt
Requires-Dist: importlib-resources
Requires-Dist: alive-progress
Requires-Dist: earthengine-api
Requires-Dist: eemont
Requires-Dist: geedim
Requires-Dist: geemap
Requires-Dist: pyyaml
Requires-Dist: termcolor
Requires-Dist: yamale
Requires-Dist: importlib-metadata ; python_version < "3.8"
Provides-Extra: testing
Requires-Dist: setuptools ; extra == 'testing'
Requires-Dist: pytest ; extra == 'testing'
Requires-Dist: pytest-cov ; extra == 'testing'
Requires-Dist: pytest-sugar ; extra == 'testing'
